st2auth_vault_backend/__init__.py
st2auth_vault_backend/vault.py
tests/__init__.py
tests/unit/__init__.py
tests/unit/test_vault_backend.py
st2_auth_backend_vault-0.3.0.dist-info/METADATA
st2_auth_backend_vault-0.3.0.dist-info/WHEEL
st2_auth_backend_vault-0.3.0.dist-info/entry_points.txt
st2_auth_backend_vault-0.3.0.dist-info/top_level.txt
st2_auth_backend_vault-0.3.0.dist-info/RECORD
